MANIFEST.in
README.rst
setup.py
epaycosdk/__init__.py
epaycosdk/client.py
epaycosdk/epayco.py
epaycosdk/errors.py
epaycosdk/resources.py
epaycosdk/test/__init__.py
epaycosdk/utils/__init__.py
epaycosdk/utils/key_lang.json
epaycosdk/utils/key_lang_apify.json
epaycosdk_win.egg-info/PKG-INFO
epaycosdk_win.egg-info/SOURCES.txt
epaycosdk_win.egg-info/dependency_links.txt
epaycosdk_win.egg-info/requires.txt
epaycosdk_win.egg-info/top_level.txt