Metadata-Version: 1.1
Name: epaycosdk-win
Version: 3.1.0
Summary: Python library for ePayco Payment API
Home-page: https://epayco.co/
Author: ePayco Development Team
Author-email: ricardo.saldarriaga@epayco.co
License: MIT
Download-URL: https://github.com/epayco/epayco-python
Platform: UNKNOWN
